gqylpy_exception/__init__.py
gqylpy_exception/g exception.py
gqylpy_exception-3.1.2.dist-info/LICENSE
gqylpy_exception-3.1.2.dist-info/METADATA
gqylpy_exception-3.1.2.dist-info/WHEEL
gqylpy_exception-3.1.2.dist-info/top_level.txt
gqylpy_exception-3.1.2.dist-info/RECORD
